LICENSE
README.md
setup.cfg
setup.py
cmdfns/__init__.py
cmdfns/command.py
cmdfns/command_cls.py
cmdfns/command_executor.py
cmdfns/command_store.py
cmdfns/dict_command_store.py
cmdfns/file_system_command_store.py
cmdfns/invalid_argument.py
cmdfns/main.py
cmdfns/py.typed
cmdfns.egg-info/PKG-INFO
cmdfns.egg-info/SOURCES.txt
cmdfns.egg-info/dependency_links.txt
cmdfns.egg-info/requires.txt
cmdfns.egg-info/top_level.txt