Metadata-Version: 2.1
Name: cmdfns
Version: 0.5.0
Summary: Make Python functions callable from the command-line
Home-page: https://github.com/aozine/cmdfns
Author: Marc Hull
Author-email: aozine@gmail.com
License: MIT
Keywords: command-line
Platform: UNKNOWN
Classifier: Development Status :: 3 - Alpha
Classifier: Intended Audience :: Developers
Classifier: License :: OSI Approved :: MIT License
Classifier: Programming Language :: Python :: 3
Classifier: Programming Language :: Python :: 3.7
Classifier: Programming Language :: Python :: 3.8
Classifier: Programming Language :: Python :: 3.9
Classifier: Programming Language :: Python :: 3.10
Requires-Python: >=3.7
License-File: LICENSE
